collresolve.cpython-39-x86_64-linux-gnu.so
collresolve-1.3.dist-info/RECORD
collresolve-1.3.dist-info/METADATA
collresolve-1.3.dist-info/LICENSE
collresolve-1.3.dist-info/top_level.txt
collresolve-1.3.dist-info/WHEEL
