Metadata-Version: 2.1
Name: collresolve
Version: 1.3
Summary: Analyse and predict outcomes of collision in N-body
Home-page: https://github.com/aemsenhuber/collresolve
Author: Alexandre Emsenhuber
Author-email: emsenhuber@lpl.arizona.edu
License: UNKNOWN
Platform: UNKNOWN
Classifier: Programming Language :: Python :: 3
Classifier: License :: OSI Approved :: Apache Software License
Classifier: Intended Audience :: Science/Research
